deareis/CHANGELOG.md
deareis/CONTRIBUTORS
deareis/COPYRIGHT
deareis/LICENSE
deareis/README.md
deareis/__init__.py
deareis/__main__.py
deareis/arguments.py
deareis/enums.py
deareis/exceptions.py
deareis/signals.py
deareis/state.py
deareis/themes.py
deareis/utility.py
deareis/version.py
deareis/LICENSES/LICENSE-DRT-from-Loewner-framework.txt
deareis/LICENSES/LICENSE-DRT-python-code.txt
deareis/LICENSES/LICENSE-DearPyGui.txt
deareis/LICENSES/LICENSE-Elchemea Analytical.txt
deareis/LICENSES/LICENSE-Jinja.txt
deareis/LICENSES/LICENSE-circuitikz.txt
deareis/LICENSES/LICENSE-cvxopt.txt
deareis/LICENSES/LICENSE-impedance.py.txt
deareis/LICENSES/LICENSE-kvxopt.txt
deareis/LICENSES/LICENSE-lmfit.txt
deareis/LICENSES/LICENSE-matplotlib.txt
deareis/LICENSES/LICENSE-nearestSPD.txt
deareis/LICENSES/LICENSE-numdifftools.txt
deareis/LICENSES/LICENSE-numpy.txt
deareis/LICENSES/LICENSE-odfpy.txt
deareis/LICENSES/LICENSE-openpyxl.txt
deareis/LICENSES/LICENSE-pandas.txt
deareis/LICENSES/LICENSE-pyDRTtools.txt
deareis/LICENSES/LICENSE-pyimpspec.txt
deareis/LICENSES/LICENSE-requests.txt
deareis/LICENSES/LICENSE-schemdraw.txt
deareis/LICENSES/LICENSE-scipy.txt
deareis/LICENSES/LICENSE-statsmodels.txt
deareis/LICENSES/LICENSE-sympy.txt
deareis/LICENSES/LICENSE-tabulate.txt
deareis/LICENSES/LICENSE-tol_colors.txt
deareis/LICENSES/LICENSE-xdg.txt
deareis/LICENSES/README.md
deareis/api/__init__.py
deareis/api/_utility.py
deareis/api/data.py
deareis/api/drt.py
deareis/api/fitting.py
deareis/api/kramers_kronig.py
deareis/api/plotting.py
deareis/api/simulation.py
deareis/api/zhit.py
deareis/api/circuit/__init__.py
deareis/api/circuit/elements.py
deareis/api/plot/__init__.py
deareis/api/plot/mpl/__init__.py
deareis/api/plot/mpl/mpl.py
deareis/config/__init__.py
deareis/config/defaults.py
deareis/data/__init__.py
deareis/data/data_sets.py
deareis/data/drt.py
deareis/data/fitting.py
deareis/data/kramers_kronig.py
deareis/data/plotting.py
deareis/data/project.py
deareis/data/simulation.py
deareis-5.1.1.dist-info/LICENSE
deareis-5.1.1.dist-info/METADATA
deareis-5.1.1.dist-info/WHEEL
deareis-5.1.1.dist-info/entry_points.txt
deareis-5.1.1.dist-info/top_level.txt
deareis-5.1.1.dist-info/RECORD
