Metadata-Version: 2.2
Name: deareis
Version: 5.1.1
Summary: A GUI program for analyzing, simulating, and visualizing impedance spectra.
Home-page: https://vyrjana.github.io/DearEIS
Author: DearEIS developers
License: GPLv3
Project-URL: Documentation, https://vyrjana.github.io/DearEIS/api/
Project-URL: Source Code, https://github.com/vyrjana/DearEIS
Project-URL: Bug Tracker, https://github.com/vyrjana/DearEIS/issues
Classifier: Intended Audience :: Science/Research
Classifier: License :: OSI Approved :: GNU General Public License v3 (GPLv3)
Classifier: Operating System :: MacOS
Classifier: Operating System :: Microsoft :: Windows
Classifier: Operating System :: POSIX :: Linux
Classifier: Programming Language :: Python :: 3.10
Classifier: Programming Language :: Python :: 3.11
Classifier: Programming Language :: Python :: 3.12
Classifier: Programming Language :: Python :: 3.13
Classifier: Programming Language :: Python :: 3 :: Only
Classifier: Topic :: Scientific/Engineering :: Chemistry
Classifier: Topic :: Scientific/Engineering :: Physics
Classifier: Topic :: Scientific/Engineering
Requires-Python: >=3.10
License-File: LICENSE
Requires-Dist: dearpygui~=2.0; python_version >= "3.13"
Requires-Dist: dearpygui~=1.11; python_version <= "3.12"
Requires-Dist: requests~=2.32
Requires-Dist: pyimpspec~=5.1
Provides-Extra: cvxopt
Requires-Dist: cvxopt~=1.3; extra == "cvxopt"
Provides-Extra: kvxopt
Requires-Dist: kvxopt~=1.3; extra == "kvxopt"
Provides-Extra: dev
Requires-Dist: build~=1.2; extra == "dev"
Requires-Dist: flake8~=7.1; extra == "dev"
Requires-Dist: setuptools~=75.3; extra == "dev"
Requires-Dist: sphinx~=8.1; extra == "dev"
Requires-Dist: sphinx-rtd-theme~=3.0; extra == "dev"
Dynamic: author
Dynamic: classifier
Dynamic: description
Dynamic: description-content-type
Dynamic: home-page
Dynamic: license
Dynamic: project-url
Dynamic: provides-extra
Dynamic: requires-dist
Dynamic: requires-python
Dynamic: summary
